Workbook
Name Aporte: Planilha2!$D$17
Name Rendimentos_Carteira: Planilha2!$D$12
Name Salario: Planilha2!$D$11
Name Sugestao_de_Investimento: Planilha2!$D$13

Sheet Auxiliar
B1: Quanto investir por mês?
B2: Por quanto anos? | F2: Agressivo
B3: Taxa de rendimento mensal? | F3: Conservador
F4: Moderado
B5: Patrimônio acumulado?
B6: Dividendos mensais?
A9: CHAVE | B9: PERFIL | C9: TIPO DE FII | D9: %
A10: =B10&"-"&C10 -> Conservador-PAPEL | B10: Conservador | C10: PAPEL | D10: 0.3
A11: =B11&"-"&C11 -> Conservador-TIJOLO | B11: Conservador | C11: TIJOLO | D11: 0.5
A12: =B12&"-"&C12 -> Conservador-HÍBRIDOS | B12: Conservador | C12: HÍBRIDOS | D12: 0.1
A13: =B13&"-"&C13 -> Conservador-FOFs | B13: Conservador | C13: FOFs | D13: 0.1
A14: =B14&"-"&C14 -> Conservador-DESENVOLVIMENTO | B14: Conservador | C14: DESENVOLVIMENTO | D14: 0
A15: =B15&"-"&C15 -> Conservador-HOTELARIAS | B15: Conservador | C15: HOTELARIAS | D15: 0
A16: =B16&"-"&C16 -> Moderado-PAPEL | B16: Moderado | C16: PAPEL | D16: 0.32
A17: =B17&"-"&C17 -> Moderado-TIJOLO | B17: Moderado | C17: TIJOLO | D17: 0.4
A18: =B18&"-"&C18 -> Moderado-HÍBRIDOS | B18: Moderado | C18: HÍBRIDOS | D18: 0.08
A19: =B19&"-"&C19 -> Moderado-FOFs | B19: Moderado | C19: FOFs | D19: 0.1
A20: =B20&"-"&C20 -> Moderado-DESENVOLVIMENTO | B20: Moderado | C20: DESENVOLVIMENTO | D20: 0.05
A21: =B21&"-"&C21 -> Moderado-HOTELARIAS | B21: Moderado | C21: HOTELARIAS | D21: 0.05
... A27: =B27&"-"&C27 -> Agressivo-HOTELARIAS | B27: Agressivo | C27: HOTELARIAS | D27: 0.1

Sheet Planilha2
B10: Configurações
B11: Salário | D11: 4500
B12: Rendimentos Carteira | D12: 0.0085
B13: Sugestão de Investimento (30%) | D13: =Salario*30% -> 1350
B15: INVESTIMENTO MENSAL
B17: Quanto investir por mês? | D17: 525
B18: Por quanto anos? | D18: 10
B19: Taxa de rendimento mensal? | D19: 0.01079
B20: Patrimônio acumulado? | D20: =FV(D19,D18*12,Aporte)*(-1) -> 127724.21
B21: Dividendos mensais? | D21: =D20*Rendimentos_Carteira -> 1085.6558
B24: Cenários | D24: Dividendos
B25: Quanto em 2 anos? | C25: =FV(D19,2*12,Aporte)*(-1) -> 14294.504 | D25: =C25*Rendimentos_Carteira -> 121.50329
B26: Quanto em 5 anos? | C26: =FV(D19,5*12,Aporte)*(-1) -> 43982.88 | D26: =C26*Rendimentos_Carteira -> 373.85448
B27: Quanto em 10 anos? | C27: =FV(D19,10*12,Aporte)*(-1) -> 127724.21 | D27: =C27*Rendimentos_Carteira -> 1085.6558
B28: Quanto em 15 anos? | C28: =FV(D19,15*12,Aporte)*(-1) -> 287163.76 | D28: =C28*Rendimentos_Carteira -> 2440.892
B29: Quanto em 20 anos? | C29: =FV(D19,20*12,Aporte)*(-1) -> 590729.16 | D29: =C29*Rendimentos_Carteira -> 5021.1979
B30: Quanto em 25 anos? | C30: =FV(D19,25*12,Aporte)*(-1) -> 1168703.4 | D30: =C30*Rendimentos_Carteira -> 9933.9787
B31: Quanto em 30 anos? | C31: =FV(D19,30*12,Aporte)*(-1) -> 2269139.1 | D31: =C31*Rendimentos_Carteira -> 19287.682
B34: PERFIL | C34: Conservador
B35: VALOR A SER INVESTIDO POR MÊS | C35: =Aporte -> 525
B38: TIPO DE FII | C38: Percentual Sugerido | D38: Valores
B39: PAPEL | C39: =VLOOKUP($C$34&"-"&B39,Auxiliar!$A$10:$D$27,4,FALSE) -> 0.3 | D39: =C39*$C$35 -> 157.5
B40: TIJOLO | C40: =VLOOKUP($C$34&"-"&B40,Auxiliar!$A$10:$D$27,4,FALSE) -> 0.5 | D40: =C40*$C$35 -> 262.5
B41: HÍBRIDOS | C41: =VLOOKUP($C$34&"-"&B41,Auxiliar!$A$10:$D$27,4,FALSE) -> 0.1 | D41: =C41*$C$35 -> 52.5
B42: FOFs | C42: =VLOOKUP($C$34&"-"&B42,Auxiliar!$A$10:$D$27,4,FALSE) -> 0.1 | D42: =C42*$C$35 -> 52.5
B43: DESENVOLVIMENTO | C43: =VLOOKUP($C$34&"-"&B43,Auxiliar!$A$10:$D$27,4,FALSE) -> 0 | D43: =C43*$C$35 -> 0
B44: HOTELARIAS | C44: =VLOOKUP($C$34&"-"&B44,Auxiliar!$A$10:$D$27,4,FALSE) -> 0 | D44: =C44*$C$35 -> 0
D45: =SUM(D39:D44) -> 525
